premier/__init__.py
premier/_logs.py
premier/cache.py
premier/interface.py
premier/main.py
premier/py.typed
premier/retry.py
premier/timer.py
premier/.claude/settings.local.json
premier/asgi/__init__.py
premier/asgi/forward.py
premier/asgi/gateway.py
premier/asgi/loadbalancer.py
premier/dashboard/__init__.py
premier/dashboard/dashboard.html
premier/dashboard/dashboard.py
premier/dashboard/service.py
premier/providers/__init__.py
premier/providers/interace.py
premier/providers/memory.py
premier/providers/redis.py
premier/throttler/__init__.py
premier/throttler/api.py
premier/throttler/errors.py
premier/throttler/handler.py
premier/throttler/interface.py
premier/throttler/throttler.py
premier-0.4.9.dist-info/METADATA
premier-0.4.9.dist-info/WHEEL
premier-0.4.9.dist-info/licenses/LICENSE
premier-0.4.9.dist-info/RECORD
