Metadata-Version: 2.4
Name: premier
Version: 0.4.9
Summary: an extendable toolbox for scalable apis
License-File: LICENSE
Classifier: Development Status :: 5 - Production/Stable
Classifier: Intended Audience :: Developers
Classifier: Intended Audience :: Information Technology
Classifier: Intended Audience :: System Administrators
Classifier: License :: OSI Approved :: MIT License
Classifier: Operating System :: OS Independent
Classifier: Programming Language :: Python :: 3 :: Only
Classifier: Programming Language :: Python :: 3.10
Classifier: Programming Language :: Python :: 3.11
Classifier: Programming Language :: Python :: 3.12
Classifier: Programming Language :: Python :: 3.13
Classifier: Topic :: Software Development
Classifier: Topic :: Software Development :: Libraries
Classifier: Topic :: Software Development :: Libraries :: Application Frameworks
Classifier: Topic :: Software Development :: Libraries :: Python Modules
Classifier: Typing :: Typed
Requires-Python: >=3.10
Requires-Dist: pyyaml>=6.0.2
Requires-Dist: typing-extensions>=4.14.0
Provides-Extra: aiohttp
Requires-Dist: aiohttp; extra == 'aiohttp'
Provides-Extra: redis
Requires-Dist: redis; extra == 'redis'
Provides-Extra: uvicorn
Requires-Dist: uvicorn; extra == 'uvicorn'
